{
	"animations": [
		{
			"offsets": [
				0,
				0
			],
			"indices": [],
			"fps": 24,
			"anim": "idle",
			"loop": false,
			"name": "idle"
		},
		{
			"offsets": [
				2,
				-4
			],
			"indices": [],
			"fps": 24,
			"anim": "singLEFT",
			"loop": false,
			"name": "left"
		},
		{
			"offsets": [
				48,
				-3
			],
			"indices": [],
			"fps": 24,
			"anim": "singRIGHT",
			"loop": false,
			"name": "right"
		},
		{
			"offsets": [
				-27,
				9
			],
			"indices": [],
			"fps": 24,
			"anim": "singUP",
			"loop": false,
			"name": "up"
		},
		{
			"offsets": [
				30,
				-6
			],
			"indices": [],
			"fps": 24,
			"anim": "singDOWN",
			"loop": false,
			"name": "down"
		}
	],
	"no_antialiasing": false,
	"image": "characters/state",
	"position": [
		0,
		40
	],
	"healthicon": "pico",
	"flip_x": true,
	"healthbar_colors": [
		183,
		216,
		85
	],
	"camera_position": [
		70,
		20
	],
	"sing_duration": 4,
	"scale": 1
}